openai_wrapper/__init__.py
openai_wrapper/chat_completion.py
openai_wrapper/completion.py
openai_wrapper/config.py
openai_wrapper/embeddings.py
openai_wrapper-0.7.0.dist-info/METADATA
openai_wrapper-0.7.0.dist-info/WHEEL
openai_wrapper-0.7.0.dist-info/RECORD
